rgb_framework/__init__.py
rgb_framework/colors.py
rgb_framework/images.py
rgb_framework/utils.py
rgb_framework-0.1.0.dist-info/licenses/LICENSE
tests/__init__.py
tests/test_colors.py
rgb_framework-0.1.0.dist-info/METADATA
rgb_framework-0.1.0.dist-info/WHEEL
rgb_framework-0.1.0.dist-info/top_level.txt
rgb_framework-0.1.0.dist-info/RECORD
