Metadata-Version: 2.4
Name: rgb-framework
Version: 0.1.0
Summary: A lightweight framework for working with RGB colors and images.
Author-email: Nandakrishnan O <nandakrishnan1311@gmail.com>
License: MIT
License-File: LICENSE
Requires-Dist: pillow
Dynamic: license-file
